README.md
setup.cfg
setup.py
TOPSIS_Shambhavi_101816051/topsis_shambhavi.py
TOPSIS_Shambhavi_101816051.egg-info/PKG-INFO
TOPSIS_Shambhavi_101816051.egg-info/SOURCES.txt
TOPSIS_Shambhavi_101816051.egg-info/dependency_links.txt
TOPSIS_Shambhavi_101816051.egg-info/entry_points.txt
TOPSIS_Shambhavi_101816051.egg-info/requires.txt
TOPSIS_Shambhavi_101816051.egg-info/top_level.txt